CMakeLists.txt
Config.cmake.in
LICENSE.txt
README.md
pyproject.toml
setup.py
./inkcpp/CMakeLists.txt
./inkcpp/array.h
./inkcpp/avl_array.h
./inkcpp/casting.h
./inkcpp/choice.cpp
./inkcpp/container_operations.cpp
./inkcpp/container_operations.h
./inkcpp/executioner.h
./inkcpp/functional.cpp
./inkcpp/functions.cpp
./inkcpp/functions.h
./inkcpp/globals_impl.cpp
./inkcpp/globals_impl.h
./inkcpp/header.cpp
./inkcpp/list_impl.cpp
./inkcpp/list_impl.h
./inkcpp/list_operations.cpp
./inkcpp/list_operations.h
./inkcpp/list_table.cpp
./inkcpp/list_table.h
./inkcpp/numeric_operations.cpp
./inkcpp/numeric_operations.h
./inkcpp/operation_bases.h
./inkcpp/operations.h
./inkcpp/output.cpp
./inkcpp/output.h
./inkcpp/platform.h
./inkcpp/random.h
./inkcpp/runner_impl.cpp
./inkcpp/runner_impl.h
./inkcpp/simple_restorable_stack.h
./inkcpp/snapshot_impl.cpp
./inkcpp/snapshot_impl.h
./inkcpp/snapshot_interface.h
./inkcpp/stack.cpp
./inkcpp/stack.h
./inkcpp/story_impl.cpp
./inkcpp/story_impl.h
./inkcpp/story_ptr.cpp
./inkcpp/string_operations.cpp
./inkcpp/string_operations.h
./inkcpp/string_table.cpp
./inkcpp/string_table.h
./inkcpp/string_utils.h
./inkcpp/system.cpp
./inkcpp/tuple.hpp
./inkcpp/value.cpp
./inkcpp/value.h
./inkcpp/collections/restorable.cpp
./inkcpp/collections/restorable.h
./inkcpp/include/choice.h
./inkcpp/include/functional.h
./inkcpp/include/globals.h
./inkcpp/include/list.h
./inkcpp/include/runner.h
./inkcpp/include/snapshot.h
./inkcpp/include/story.h
./inkcpp/include/story_ptr.h
./inkcpp/include/traits.h
./inkcpp/include/types.h
./inkcpp_compiler/CMakeLists.txt
./inkcpp_compiler/binary_emitter.cpp
./inkcpp_compiler/binary_emitter.h
./inkcpp_compiler/binary_stream.cpp
./inkcpp_compiler/binary_stream.h
./inkcpp_compiler/command.cpp
./inkcpp_compiler/compiler.cpp
./inkcpp_compiler/emitter.cpp
./inkcpp_compiler/emitter.h
./inkcpp_compiler/json.hpp
./inkcpp_compiler/json_compiler.cpp
./inkcpp_compiler/json_compiler.h
./inkcpp_compiler/list_data.cpp
inkcpp_py.egg-info/PKG-INFO
inkcpp_py.egg-info/SOURCES.txt
inkcpp_py.egg-info/dependency_links.txt
inkcpp_py.egg-info/not-zip-safe
inkcpp_py.egg-info/top_level.txt
