Metadata-Version: 2.4
Name: inkcpp-py
Version: 0.1.10
Summary: Python bindings for InkCPP a Inkle runtime written in C++
Author: Julian Benda
Author-email: julian.benda@ovgu.de
License: MIT License
Project-URL: Repository, https://github.com/JBenda/inkcpp.git
Project-URL: Issues, https://github.com/JBenda/inkcpp/issues
Keywords: ink,inkpp,inklecate
Requires-Python: >=3.7
License-File: LICENSE.txt
Dynamic: author
Dynamic: author-email
Dynamic: license-file
Dynamic: requires-python
Dynamic: summary
